{
  "parent": "minecraft:block/block",
  "textures": {
    "tex": "runeworld:block/cairn",
    "particle": "#tex"
  },
  "elements": [
    {
      "from": [
        6,
        13,
        6
      ],
      "to": [
        9,
        14,
        9
      ],
      "rotation": {
        "origin": [
          7,
          26,
          7
        ],
        "axis": "y",
        "angle": -22.5
      },
      "faces": {
        "down": {
          "texture": "#tex",
          "uv": [
            0.0,
            0.0,
            3.0,
            3.0
          ]
        },
        "up": {
          "texture": "#tex",
          "uv": [
            0.0,
            0.0,
            3.0,
            3.0
          ]
        },
        "north": {
          "texture": "#tex",
          "uv": [
            0.0,
            0.0,
            3.0,
            1.0
          ]
        },
        "south": {
          "texture": "#tex",
          "uv": [
            0.0,
            0.0,
            3.0,
            1.0
          ]
        },
        "west": {
          "texture": "#tex",
          "uv": [
            0.0,
            0.0,
            3.0,
            1.0
          ]
        },
        "east": {
          "texture": "#tex",
          "uv": [
            0.0,
            0.0,
            3.0,
            1.0
          ]
        }
      }
    }
  ]
}